browsergym/webarena_verified/__init__.py
browsergym/webarena_verified/config.py
browsergym/webarena_verified/evaluators.py
browsergym/webarena_verified/task.py
browsergym_webarena_verified-0.14.3.dist-info/METADATA
browsergym_webarena_verified-0.14.3.dist-info/WHEEL
browsergym_webarena_verified-0.14.3.dist-info/RECORD
